{
    "type": "raid",
    "maxStages": 1000,
    "timeLimit": 60,
    "enemies": {
        "Room 1": "9.90e+56",
        "Room 2": "1.09e+57",
        "Room 3": "1.20e+57",
        "Room 4": "1.32e+57",
        "Room 5": "1.45e+57",
        "Room 6": "1.59e+57",
        "Room 7": "1.75e+57",
        "Room 8": "1.93e+57",
        "Room 9": "2.12e+57",
        "Room 10": "2.33e+57",
        "Room 11": "2.57e+57",
        "Room 12": "2.82e+57",
        "Room 13": "3.11e+57",
        "Room 14": "3.42e+57",
        "Room 15": "3.76e+57",
        "Room 16": "4.14e+57",
        "Room 17": "4.55e+57",
        "Room 18": "5.00e+57",
        "Room 19": "5.50e+57",
        "Room 20": "6.05e+57",
        "Room 21": "6.66e+57",
        "Room 22": "7.33e+57",
        "Room 23": "8.06e+57",
        "Room 24": "8.86e+57",
        "Room 25": "9.75e+57",
        "Room 26": "1.07e+58",
        "Room 27": "1.18e+58",
        "Room 28": "1.30e+58",
        "Room 29": "1.43e+58",
        "Room 30": "1.57e+58",
        "Room 31": "1.73e+58",
        "Room 32": "1.90e+58",
        "Room 33": "2.09e+58",
        "Room 34": "2.30e+58",
        "Room 35": "2.53e+58",
        "Room 36": "2.78e+58",
        "Room 37": "3.06e+58",
        "Room 38": "3.37e+58",
        "Room 39": "3.70e+58",
        "Room 40": "4.07e+58",
        "Room 41": "4.48e+58",
        "Room 42": "4.93e+58",
        "Room 43": "5.42e+58",
        "Room 44": "5.96e+58",
        "Room 45": "6.56e+58",
        "Room 46": "7.22e+58",
        "Room 47": "7.94e+58",
        "Room 48": "8.73e+58",
        "Room 49": "9.61e+58",
        "Room 50": "1.06e+59",
        "Room 51": "1.16e+59",
        "Room 52": "1.28e+59",
        "Room 53": "1.41e+59",
        "Room 54": "1.55e+59",
        "Room 55": "1.70e+59",
        "Room 56": "1.87e+59",
        "Room 57": "2.06e+59",
        "Room 58": "2.26e+59",
        "Room 59": "2.49e+59",
        "Room 60": "2.74e+59",
        "Room 61": "3.01e+59",
        "Room 62": "3.32e+59",
        "Room 63": "3.65e+59",
        "Room 64": "4.01e+59",
        "Room 65": "4.41e+59",
        "Room 66": "4.85e+59",
        "Room 67": "5.34e+59",
        "Room 68": "5.87e+59",
        "Room 69": "6.46e+59",
        "Room 70": "7.11e+59",
        "Room 71": "7.82e+59",
        "Room 72": "8.60e+59",
        "Room 73": "9.46e+59",
        "Room 74": "1.04e+60",
        "Room 75": "1.14e+60",
        "Room 76": "1.26e+60",
        "Room 77": "1.39e+60",
        "Room 78": "1.52e+60",
        "Room 79": "1.68e+60",
        "Room 80": "1.84e+60",
        "Room 81": "2.03e+60",
        "Room 82": "2.23e+60",
        "Room 83": "2.45e+60",
        "Room 84": "2.70e+60",
        "Room 85": "2.97e+60",
        "Room 86": "3.27e+60",
        "Room 87": "3.59e+60",
        "Room 88": "3.95e+60",
        "Room 89": "4.35e+60",
        "Room 90": "4.78e+60",
        "Room 91": "5.26e+60",
        "Room 92": "5.79e+60",
        "Room 93": "6.36e+60",
        "Room 94": "7.00e+60",
        "Room 95": "7.70e+60",
        "Room 96": "8.47e+60",
        "Room 97": "9.32e+60",
        "Room 98": "1.03e+61",
        "Room 99": "1.13e+61",
        "Room 100": "1.24e+61",
        "Room 101": "1.36e+61",
        "Room 102": "1.50e+61",
        "Room 103": "1.65e+61",
        "Room 104": "1.82e+61",
        "Room 105": "2.00e+61",
        "Room 106": "2.20e+61",
        "Room 107": "2.42e+61",
        "Room 108": "2.66e+61",
        "Room 109": "2.92e+61",
        "Room 110": "3.22e+61",
        "Room 111": "3.54e+61",
        "Room 112": "3.89e+61",
        "Room 113": "4.28e+61",
        "Room 114": "4.71e+61",
        "Room 115": "5.18e+61",
        "Room 116": "5.70e+61",
        "Room 117": "6.27e+61",
        "Room 118": "6.90e+61",
        "Room 119": "7.59e+61",
        "Room 120": "8.34e+61",
        "Room 121": "9.18e+61",
        "Room 122": "1.01e+62",
        "Room 123": "1.11e+62",
        "Room 124": "1.22e+62",
        "Room 125": "1.34e+62",
        "Room 126": "1.48e+62",
        "Room 127": "1.63e+62",
        "Room 128": "1.79e+62",
        "Room 129": "1.97e+62",
        "Room 130": "2.16e+62",
        "Room 131": "2.38e+62",
        "Room 132": "2.62e+62",
        "Room 133": "2.88e+62",
        "Room 134": "3.17e+62",
        "Room 135": "3.49e+62",
        "Room 136": "3.83e+62",
        "Room 137": "4.22e+62",
        "Room 138": "4.64e+62",
        "Room 139": "5.10e+62",
        "Room 140": "5.61e+62",
        "Room 141": "6.17e+62",
        "Room 142": "6.79e+62",
        "Room 143": "7.47e+62",
        "Room 144": "8.22e+62",
        "Room 145": "9.04e+62",
        "Room 146": "9.94e+62",
        "Room 147": "1.09e+63",
        "Room 148": "1.20e+63",
        "Room 149": "1.32e+63",
        "Room 150": "1.46e+63",
        "Room 151": "1.60e+63",
        "Room 152": "1.76e+63",
        "Room 153": "1.94e+63",
        "Room 154": "2.13e+63",
        "Room 155": "2.34e+63",
        "Room 156": "2.58e+63",
        "Room 157": "2.84e+63",
        "Room 158": "3.12e+63",
        "Room 159": "3.43e+63",
        "Room 160": "3.78e+63",
        "Room 161": "4.15e+63",
        "Room 162": "4.57e+63",
        "Room 163": "5.03e+63",
        "Room 164": "5.53e+63",
        "Room 165": "6.08e+63",
        "Room 166": "6.69e+63",
        "Room 167": "7.36e+63",
        "Room 168": "8.09e+63",
        "Room 169": "8.90e+63",
        "Room 170": "9.79e+63",
        "Room 171": "1.08e+64",
        "Room 172": "1.19e+64",
        "Room 173": "1.30e+64",
        "Room 174": "1.43e+64",
        "Room 175": "1.58e+64",
        "Room 176": "1.74e+64",
        "Room 177": "1.91e+64",
        "Room 178": "2.10e+64",
        "Room 179": "2.31e+64",
        "Room 180": "2.54e+64",
        "Room 181": "2.80e+64",
        "Room 182": "3.07e+64",
        "Room 183": "3.38e+64",
        "Room 184": "3.72e+64",
        "Room 185": "4.09e+64",
        "Room 186": "4.50e+64",
        "Room 187": "4.95e+64",
        "Room 188": "5.45e+64",
        "Room 189": "5.99e+64",
        "Room 190": "6.59e+64",
        "Room 191": "7.25e+64",
        "Room 192": "7.97e+64",
        "Room 193": "8.77e+64",
        "Room 194": "9.65e+64",
        "Room 195": "1.06e+65",
        "Room 196": "1.17e+65",
        "Room 197": "1.28e+65",
        "Room 198": "1.41e+65",
        "Room 199": "1.55e+65",
        "Room 200": "1.71e+65",
        "Room 201": "1.88e+65",
        "Room 202": "2.07e+65",
        "Room 203": "2.27e+65",
        "Room 204": "2.50e+65",
        "Room 205": "2.75e+65",
        "Room 206": "3.03e+65",
        "Room 207": "3.33e+65",
        "Room 208": "3.66e+65",
        "Room 209": "4.03e+65",
        "Room 210": "4.43e+65",
        "Room 211": "4.88e+65",
        "Room 212": "5.36e+65",
        "Room 213": "5.90e+65",
        "Room 214": "6.49e+65",
        "Room 215": "7.14e+65",
        "Room 216": "7.85e+65",
        "Room 217": "8.64e+65",
        "Room 218": "9.50e+65",
        "Room 219": "1.05e+66",
        "Room 220": "1.15e+66",
        "Room 221": "1.26e+66",
        "Room 222": "1.39e+66",
        "Room 223": "1.53e+66",
        "Room 224": "1.68e+66",
        "Room 225": "1.85e+66",
        "Room 226": "2.04e+66",
        "Room 227": "2.24e+66",
        "Room 228": "2.46e+66",
        "Room 229": "2.71e+66",
        "Room 230": "2.98e+66",
        "Room 231": "3.28e+66",
        "Room 232": "3.61e+66",
        "Room 233": "3.97e+66",
        "Room 234": "4.37e+66",
        "Room 235": "4.80e+66",
        "Room 236": "5.28e+66",
        "Room 237": "5.81e+66",
        "Room 238": "6.39e+66",
        "Room 239": "7.03e+66",
        "Room 240": "7.74e+66",
        "Room 241": "8.51e+66",
        "Room 242": "9.36e+66",
        "Room 243": "1.03e+67",
        "Room 244": "1.13e+67",
        "Room 245": "1.25e+67",
        "Room 246": "1.37e+67",
        "Room 247": "1.51e+67",
        "Room 248": "1.66e+67",
        "Room 249": "1.82e+67",
        "Room 250": "2.01e+67",
        "Room 251": "2.21e+67",
        "Room 252": "2.43e+67",
        "Room 253": "2.67e+67",
        "Room 254": "2.94e+67",
        "Room 255": "3.23e+67",
        "Room 256": "3.55e+67",
        "Room 257": "3.91e+67",
        "Room 258": "4.30e+67",
        "Room 259": "4.73e+67",
        "Room 260": "5.20e+67",
        "Room 261": "5.72e+67",
        "Room 262": "6.30e+67",
        "Room 263": "6.93e+67",
        "Room 264": "7.62e+67",
        "Room 265": "8.38e+67",
        "Room 266": "9.22e+67",
        "Room 267": "1.01e+68",
        "Room 268": "1.12e+68",
        "Room 269": "1.23e+68",
        "Room 270": "1.35e+68",
        "Room 271": "1.48e+68",
        "Room 272": "1.63e+68",
        "Room 273": "1.80e+68",
        "Room 274": "1.98e+68",
        "Room 275": "2.17e+68",
        "Room 276": "2.39e+68",
        "Room 277": "2.63e+68",
        "Room 278": "2.89e+68",
        "Room 279": "3.18e+68",
        "Room 280": "3.50e+68",
        "Room 281": "3.85e+68",
        "Room 282": "4.24e+68",
        "Room 283": "4.66e+68",
        "Room 284": "5.13e+68",
        "Room 285": "5.64e+68",
        "Room 286": "6.20e+68",
        "Room 287": "6.82e+68",
        "Room 288": "7.50e+68",
        "Room 289": "8.26e+68",
        "Room 290": "9.08e+68",
        "Room 291": "9.99e+68",
        "Room 292": "1.10e+69",
        "Room 293": "1.21e+69",
        "Room 294": "1.33e+69",
        "Room 295": "1.46e+69",
        "Room 296": "1.61e+69",
        "Room 297": "1.77e+69",
        "Room 298": "1.95e+69",
        "Room 299": "2.14e+69",
        "Room 300": "2.36e+69",
        "Room 301": "2.59e+69",
        "Room 302": "2.85e+69",
        "Room 303": "3.13e+69",
        "Room 304": "3.45e+69",
        "Room 305": "3.79e+69",
        "Room 306": "4.17e+69",
        "Room 307": "4.59e+69",
        "Room 308": "5.05e+69",
        "Room 309": "5.55e+69",
        "Room 310": "6.11e+69",
        "Room 311": "6.72e+69",
        "Room 312": "7.39e+69",
        "Room 313": "8.13e+69",
        "Room 314": "8.94e+69",
        "Room 315": "9.84e+69",
        "Room 316": "1.08e+70",
        "Room 317": "1.19e+70",
        "Room 318": "1.31e+70",
        "Room 319": "1.44e+70",
        "Room 320": "1.59e+70",
        "Room 321": "1.74e+70",
        "Room 322": "1.92e+70",
        "Room 323": "2.11e+70",
        "Room 324": "2.32e+70",
        "Room 325": "2.55e+70",
        "Room 326": "2.81e+70",
        "Room 327": "3.09e+70",
        "Room 328": "3.40e+70",
        "Room 329": "3.74e+70",
        "Room 330": "4.11e+70",
        "Room 331": "4.52e+70",
        "Room 332": "4.97e+70",
        "Room 333": "5.47e+70",
        "Room 334": "6.02e+70",
        "Room 335": "6.62e+70",
        "Room 336": "7.28e+70",
        "Room 337": "8.01e+70",
        "Room 338": "8.81e+70",
        "Room 339": "9.69e+70",
        "Room 340": "1.07e+71",
        "Room 341": "1.17e+71",
        "Room 342": "1.29e+71",
        "Room 343": "1.42e+71",
        "Room 344": "1.56e+71",
        "Room 345": "1.72e+71",
        "Room 346": "1.89e+71",
        "Room 347": "2.08e+71",
        "Room 348": "2.29e+71",
        "Room 349": "2.51e+71",
        "Room 350": "2.76e+71",
        "Room 351": "3.04e+71",
        "Room 352": "3.35e+71",
        "Room 353": "3.68e+71",
        "Room 354": "4.05e+71",
        "Room 355": "4.45e+71",
        "Room 356": "4.90e+71",
        "Room 357": "5.39e+71",
        "Room 358": "5.93e+71",
        "Room 359": "6.52e+71",
        "Room 360": "7.17e+71",
        "Room 361": "7.89e+71",
        "Room 362": "8.68e+71",
        "Room 363": "9.55e+71",
        "Room 364": "1.05e+72",
        "Room 365": "1.15e+72",
        "Room 366": "1.27e+72",
        "Room 367": "1.40e+72",
        "Room 368": "1.54e+72",
        "Room 369": "1.69e+72",
        "Room 370": "1.86e+72",
        "Room 371": "2.05e+72",
        "Room 372": "2.25e+72",
        "Room 373": "2.48e+72",
        "Room 374": "2.72e+72",
        "Room 375": "3.00e+72",
        "Room 376": "3.30e+72",
        "Room 377": "3.62e+72",
        "Room 378": "3.99e+72",
        "Room 379": "4.39e+72",
        "Room 380": "4.82e+72",
        "Room 381": "5.31e+72",
        "Room 382": "5.84e+72",
        "Room 383": "6.42e+72",
        "Room 384": "7.06e+72",
        "Room 385": "7.77e+72",
        "Room 386": "8.55e+72",
        "Room 387": "9.40e+72",
        "Room 388": "1.03e+73",
        "Room 389": "1.14e+73",
        "Room 390": "1.25e+73",
        "Room 391": "1.38e+73",
        "Room 392": "1.51e+73",
        "Room 393": "1.67e+73",
        "Room 394": "1.83e+73",
        "Room 395": "2.02e+73",
        "Room 396": "2.22e+73",
        "Room 397": "2.44e+73",
        "Room 398": "2.68e+73",
        "Room 399": "2.95e+73",
        "Room 400": "3.25e+73",
        "Room 401": "3.57e+73",
        "Room 402": "3.93e+73",
        "Room 403": "4.32e+73",
        "Room 404": "4.75e+73",
        "Room 405": "5.23e+73",
        "Room 406": "5.75e+73",
        "Room 407": "6.33e+73",
        "Room 408": "6.96e+73",
        "Room 409": "7.65e+73",
        "Room 410": "8.42e+73",
        "Room 411": "9.26e+73",
        "Room 412": "1.02e+74",
        "Room 413": "1.12e+74",
        "Room 414": "1.23e+74",
        "Room 415": "1.36e+74",
        "Room 416": "1.49e+74",
        "Room 417": "1.64e+74",
        "Room 418": "1.80e+74",
        "Room 419": "1.99e+74",
        "Room 420": "2.18e+74",
        "Room 421": "2.40e+74",
        "Room 422": "2.64e+74",
        "Room 423": "2.91e+74",
        "Room 424": "3.20e+74",
        "Room 425": "3.52e+74",
        "Room 426": "3.87e+74",
        "Room 427": "4.26e+74",
        "Room 428": "4.68e+74",
        "Room 429": "5.15e+74",
        "Room 430": "5.66e+74",
        "Room 431": "6.23e+74",
        "Room 432": "6.85e+74",
        "Room 433": "7.54e+74",
        "Room 434": "8.29e+74",
        "Room 435": "9.12e+74",
        "Room 436": "1.00e+75",
        "Room 437": "1.10e+75",
        "Room 438": "1.21e+75",
        "Room 439": "1.34e+75",
        "Room 440": "1.47e+75",
        "Room 441": "1.62e+75",
        "Room 442": "1.78e+75",
        "Room 443": "1.96e+75",
        "Room 444": "2.15e+75",
        "Room 445": "2.37e+75",
        "Room 446": "2.60e+75",
        "Room 447": "2.86e+75",
        "Room 448": "3.15e+75",
        "Room 449": "3.46e+75",
        "Room 450": "3.81e+75",
        "Room 451": "4.19e+75",
        "Room 452": "4.61e+75",
        "Room 453": "5.07e+75",
        "Room 454": "5.58e+75",
        "Room 455": "6.14e+75",
        "Room 456": "6.75e+75",
        "Room 457": "7.43e+75",
        "Room 458": "8.17e+75",
        "Room 459": "8.98e+75",
        "Room 460": "9.88e+75",
        "Room 461": "1.09e+76",
        "Room 462": "1.20e+76",
        "Room 463": "1.32e+76",
        "Room 464": "1.45e+76",
        "Room 465": "1.59e+76",
        "Room 466": "1.75e+76",
        "Room 467": "1.93e+76",
        "Room 468": "2.12e+76",
        "Room 469": "2.33e+76",
        "Room 470": "2.56e+76",
        "Room 471": "2.82e+76",
        "Room 472": "3.10e+76",
        "Room 473": "3.41e+76",
        "Room 474": "3.75e+76",
        "Room 475": "4.13e+76",
        "Room 476": "4.54e+76",
        "Room 477": "5.00e+76",
        "Room 478": "5.50e+76",
        "Room 479": "6.04e+76",
        "Room 480": "6.65e+76",
        "Room 481": "7.31e+76",
        "Room 482": "8.05e+76",
        "Room 483": "8.85e+76",
        "Room 484": "9.73e+76",
        "Room 485": "1.07e+77",
        "Room 486": "1.18e+77",
        "Room 487": "1.30e+77",
        "Room 488": "1.43e+77",
        "Room 489": "1.57e+77",
        "Room 490": "1.72e+77",
        "Room 491": "1.90e+77",
        "Room 492": "2.09e+77",
        "Room 493": "2.30e+77",
        "Room 494": "2.52e+77",
        "Room 495": "2.78e+77",
        "Room 496": "3.06e+77",
        "Room 497": "3.36e+77",
        "Room 498": "3.70e+77",
        "Room 499": "4.07e+77",
        "Room 500": "4.47e+77",
        "Room 501": "4.92e+77",
        "Room 502": "5.41e+77",
        "Room 503": "5.95e+77",
        "Room 504": "6.55e+77",
        "Room 505": "7.20e+77",
        "Room 506": "7.92e+77",
        "Room 507": "8.72e+77",
        "Room 508": "9.59e+77",
        "Room 509": "1.05e+78",
        "Room 510": "1.16e+78",
        "Room 511": "1.28e+78",
        "Room 512": "1.40e+78",
        "Room 513": "1.54e+78",
        "Room 514": "1.70e+78",
        "Room 515": "1.87e+78",
        "Room 516": "2.06e+78",
        "Room 517": "2.26e+78",
        "Room 518": "2.49e+78",
        "Room 519": "2.74e+78",
        "Room 520": "3.01e+78",
        "Room 521": "3.31e+78",
        "Room 522": "3.64e+78",
        "Room 523": "4.01e+78",
        "Room 524": "4.41e+78",
        "Room 525": "4.85e+78",
        "Room 526": "5.33e+78",
        "Room 527": "5.86e+78",
        "Room 528": "6.45e+78",
        "Room 529": "7.10e+78",
        "Room 530": "7.80e+78",
        "Room 531": "8.59e+78",
        "Room 532": "9.44e+78",
        "Room 533": "1.04e+79",
        "Room 534": "1.14e+79",
        "Room 535": "1.26e+79",
        "Room 536": "1.38e+79",
        "Room 537": "1.52e+79",
        "Room 538": "1.67e+79",
        "Room 539": "1.84e+79",
        "Room 540": "2.02e+79",
        "Room 541": "2.23e+79",
        "Room 542": "2.45e+79",
        "Room 543": "2.69e+79",
        "Room 544": "2.96e+79",
        "Room 545": "3.26e+79",
        "Room 546": "3.59e+79",
        "Room 547": "3.95e+79",
        "Room 548": "4.34e+79",
        "Room 549": "4.77e+79",
        "Room 550": "5.25e+79",
        "Room 551": "5.78e+79",
        "Room 552": "6.35e+79",
        "Room 553": "6.99e+79",
        "Room 554": "7.69e+79",
        "Room 555": "8.46e+79",
        "Room 556": "9.30e+79",
        "Room 557": "1.02e+80",
        "Room 558": "1.13e+80",
        "Room 559": "1.24e+80",
        "Room 560": "1.36e+80",
        "Room 561": "1.50e+80",
        "Room 562": "1.65e+80",
        "Room 563": "1.81e+80",
        "Room 564": "1.99e+80",
        "Room 565": "2.19e+80",
        "Room 566": "2.41e+80",
        "Room 567": "2.65e+80",
        "Room 568": "2.92e+80",
        "Room 569": "3.21e+80",
        "Room 570": "3.53e+80",
        "Room 571": "3.89e+80",
        "Room 572": "4.27e+80",
        "Room 573": "4.70e+80",
        "Room 574": "5.17e+80",
        "Room 575": "5.69e+80",
        "Room 576": "6.26e+80",
        "Room 577": "6.88e+80",
        "Room 578": "7.57e+80",
        "Room 579": "8.33e+80",
        "Room 580": "9.16e+80",
        "Room 581": "1.01e+81",
        "Room 582": "1.11e+81",
        "Room 583": "1.22e+81",
        "Room 584": "1.34e+81",
        "Room 585": "1.48e+81",
        "Room 586": "1.62e+81",
        "Room 587": "1.79e+81",
        "Room 588": "1.96e+81",
        "Room 589": "2.16e+81",
        "Room 590": "2.38e+81",
        "Room 591": "2.61e+81",
        "Room 592": "2.88e+81",
        "Room 593": "3.16e+81",
        "Room 594": "3.48e+81",
        "Room 595": "3.83e+81",
        "Room 596": "4.21e+81",
        "Room 597": "4.63e+81",
        "Room 598": "5.09e+81",
        "Room 599": "5.60e+81",
        "Room 600": "6.16e+81",
        "Room 601": "6.78e+81",
        "Room 602": "7.46e+81",
        "Room 603": "8.20e+81",
        "Room 604": "9.02e+81",
        "Room 605": "9.93e+81",
        "Room 606": "1.09e+82",
        "Room 607": "1.20e+82",
        "Room 608": "1.32e+82",
        "Room 609": "1.45e+82",
        "Room 610": "1.60e+82",
        "Room 611": "1.76e+82",
        "Room 612": "1.93e+82",
        "Room 613": "2.13e+82",
        "Room 614": "2.34e+82",
        "Room 615": "2.58e+82",
        "Room 616": "2.83e+82",
        "Room 617": "3.12e+82",
        "Room 618": "3.43e+82",
        "Room 619": "3.77e+82",
        "Room 620": "4.15e+82",
        "Room 621": "4.56e+82",
        "Room 622": "5.02e+82",
        "Room 623": "5.52e+82",
        "Room 624": "6.07e+82",
        "Room 625": "6.68e+82",
        "Room 626": "7.35e+82",
        "Room 627": "8.08e+82",
        "Room 628": "8.89e+82",
        "Room 629": "9.78e+82",
        "Room 630": "1.08e+83",
        "Room 631": "1.18e+83",
        "Room 632": "1.30e+83",
        "Room 633": "1.43e+83",
        "Room 634": "1.57e+83",
        "Room 635": "1.73e+83",
        "Room 636": "1.91e+83",
        "Room 637": "2.10e+83",
        "Room 638": "2.31e+83",
        "Room 639": "2.54e+83",
        "Room 640": "2.79e+83",
        "Room 641": "3.07e+83",
        "Room 642": "3.38e+83",
        "Room 643": "3.71e+83",
        "Room 644": "4.08e+83",
        "Room 645": "4.49e+83",
        "Room 646": "4.94e+83",
        "Room 647": "5.44e+83",
        "Room 648": "5.98e+83",
        "Room 649": "6.58e+83",
        "Room 650": "7.24e+83",
        "Room 651": "7.96e+83",
        "Room 652": "8.76e+83",
        "Room 653": "9.63e+83",
        "Room 654": "1.06e+84",
        "Room 655": "1.17e+84",
        "Room 656": "1.28e+84",
        "Room 657": "1.41e+84",
        "Room 658": "1.55e+84",
        "Room 659": "1.71e+84",
        "Room 660": "1.88e+84",
        "Room 661": "2.06e+84",
        "Room 662": "2.27e+84",
        "Room 663": "2.50e+84",
        "Room 664": "2.75e+84",
        "Room 665": "3.02e+84",
        "Room 666": "3.32e+84",
        "Room 667": "3.66e+84",
        "Room 668": "4.02e+84",
        "Room 669": "4.43e+84",
        "Room 670": "4.87e+84",
        "Room 671": "5.35e+84",
        "Room 672": "5.89e+84",
        "Room 673": "6.48e+84",
        "Room 674": "7.13e+84",
        "Room 675": "7.84e+84",
        "Room 676": "8.62e+84",
        "Room 677": "9.49e+84",
        "Room 678": "1.04e+85",
        "Room 679": "1.15e+85",
        "Room 680": "1.26e+85",
        "Room 681": "1.39e+85",
        "Room 682": "1.53e+85",
        "Room 683": "1.68e+85",
        "Room 684": "1.85e+85",
        "Room 685": "2.03e+85",
        "Room 686": "2.24e+85",
        "Room 687": "2.46e+85",
        "Room 688": "2.71e+85",
        "Room 689": "2.98e+85",
        "Room 690": "3.28e+85",
        "Room 691": "3.60e+85",
        "Room 692": "3.96e+85",
        "Room 693": "4.36e+85",
        "Room 694": "4.80e+85",
        "Room 695": "5.27e+85",
        "Room 696": "5.80e+85",
        "Room 697": "6.38e+85",
        "Room 698": "7.02e+85",
        "Room 699": "7.72e+85",
        "Room 700": "8.49e+85",
        "Room 701": "9.34e+85",
        "Room 702": "1.03e+86",
        "Room 703": "1.13e+86",
        "Room 704": "1.24e+86",
        "Room 705": "1.37e+86",
        "Room 706": "1.50e+86",
        "Room 707": "1.66e+86",
        "Room 708": "1.82e+86",
        "Room 709": "2.00e+86",
        "Room 710": "2.20e+86",
        "Room 711": "2.42e+86",
        "Room 712": "2.67e+86",
        "Room 713": "2.93e+86",
        "Room 714": "3.23e+86",
        "Room 715": "3.55e+86",
        "Room 716": "3.90e+86",
        "Room 717": "4.29e+86",
        "Room 718": "4.72e+86",
        "Room 719": "5.20e+86",
        "Room 720": "5.71e+86",
        "Room 721": "6.29e+86",
        "Room 722": "6.91e+86",
        "Room 723": "7.61e+86",
        "Room 724": "8.37e+86",
        "Room 725": "9.20e+86",
        "Room 726": "1.01e+87",
        "Room 727": "1.11e+87",
        "Room 728": "1.22e+87",
        "Room 729": "1.35e+87",
        "Room 730": "1.48e+87",
        "Room 731": "1.63e+87",
        "Room 732": "1.79e+87",
        "Room 733": "1.97e+87",
        "Room 734": "2.17e+87",
        "Room 735": "2.39e+87",
        "Room 736": "2.63e+87",
        "Room 737": "2.89e+87",
        "Room 738": "3.18e+87",
        "Room 739": "3.49e+87",
        "Room 740": "3.84e+87",
        "Room 741": "4.23e+87",
        "Room 742": "4.65e+87",
        "Room 743": "5.12e+87",
        "Room 744": "5.63e+87",
        "Room 745": "6.19e+87",
        "Room 746": "6.81e+87",
        "Room 747": "7.49e+87",
        "Room 748": "8.24e+87",
        "Room 749": "9.06e+87",
        "Room 750": "9.97e+87",
        "Room 751": "1.10e+88",
        "Room 752": "1.21e+88",
        "Room 753": "1.33e+88",
        "Room 754": "1.46e+88",
        "Room 755": "1.61e+88",
        "Room 756": "1.77e+88",
        "Room 757": "1.94e+88",
        "Room 758": "2.14e+88",
        "Room 759": "2.35e+88",
        "Room 760": "2.59e+88",
        "Room 761": "2.85e+88",
        "Room 762": "3.13e+88",
        "Room 763": "3.44e+88",
        "Room 764": "3.79e+88",
        "Room 765": "4.17e+88",
        "Room 766": "4.58e+88",
        "Room 767": "5.04e+88",
        "Room 768": "5.54e+88",
        "Room 769": "6.10e+88",
        "Room 770": "6.71e+88",
        "Room 771": "7.38e+88",
        "Room 772": "8.12e+88",
        "Room 773": "8.93e+88",
        "Room 774": "9.82e+88",
        "Room 775": "1.08e+89",
        "Room 776": "1.19e+89",
        "Room 777": "1.31e+89",
        "Room 778": "1.44e+89",
        "Room 779": "1.58e+89",
        "Room 780": "1.74e+89",
        "Room 781": "1.91e+89",
        "Room 782": "2.11e+89",
        "Room 783": "2.32e+89",
        "Room 784": "2.55e+89",
        "Room 785": "2.80e+89",
        "Room 786": "3.08e+89",
        "Room 787": "3.39e+89",
        "Room 788": "3.73e+89",
        "Room 789": "4.10e+89",
        "Room 790": "4.51e+89",
        "Room 791": "4.96e+89",
        "Room 792": "5.46e+89",
        "Room 793": "6.01e+89",
        "Room 794": "6.61e+89",
        "Room 795": "7.27e+89",
        "Room 796": "8.00e+89",
        "Room 797": "8.79e+89",
        "Room 798": "9.67e+89",
        "Room 799": "1.06e+90",
        "Room 800": "1.17e+90",
        "Room 801": "1.29e+90",
        "Room 802": "1.42e+90",
        "Room 803": "1.56e+90",
        "Room 804": "1.71e+90",
        "Room 805": "1.89e+90",
        "Room 806": "2.07e+90",
        "Room 807": "2.28e+90",
        "Room 808": "2.51e+90",
        "Room 809": "2.76e+90",
        "Room 810": "3.04e+90",
        "Room 811": "3.34e+90",
        "Room 812": "3.67e+90",
        "Room 813": "4.04e+90",
        "Room 814": "4.45e+90",
        "Room 815": "4.89e+90",
        "Room 816": "5.38e+90",
        "Room 817": "5.92e+90",
        "Room 818": "6.51e+90",
        "Room 819": "7.16e+90",
        "Room 820": "7.87e+90",
        "Room 821": "8.66e+90",
        "Room 822": "9.53e+90",
        "Room 823": "1.05e+91",
        "Room 824": "1.15e+91",
        "Room 825": "1.27e+91",
        "Room 826": "1.40e+91",
        "Room 827": "1.54e+91",
        "Room 828": "1.69e+91",
        "Room 829": "1.86e+91",
        "Room 830": "2.04e+91",
        "Room 831": "2.25e+91",
        "Room 832": "2.47e+91",
        "Room 833": "2.72e+91",
        "Room 834": "2.99e+91",
        "Room 835": "3.29e+91",
        "Room 836": "3.62e+91",
        "Room 837": "3.98e+91",
        "Room 838": "4.38e+91",
        "Room 839": "4.82e+91",
        "Room 840": "5.30e+91",
        "Room 841": "5.83e+91",
        "Room 842": "6.41e+91",
        "Room 843": "7.05e+91",
        "Room 844": "7.76e+91",
        "Room 845": "8.53e+91",
        "Room 846": "9.39e+91",
        "Room 847": "1.03e+92",
        "Room 848": "1.14e+92",
        "Room 849": "1.25e+92",
        "Room 850": "1.37e+92",
        "Room 851": "1.51e+92",
        "Room 852": "1.66e+92",
        "Room 853": "1.83e+92",
        "Room 854": "2.01e+92",
        "Room 855": "2.21e+92",
        "Room 856": "2.43e+92",
        "Room 857": "2.68e+92",
        "Room 858": "2.95e+92",
        "Room 859": "3.24e+92",
        "Room 860": "3.56e+92",
        "Room 861": "3.92e+92",
        "Room 862": "4.31e+92",
        "Room 863": "4.74e+92",
        "Room 864": "5.22e+92",
        "Room 865": "5.74e+92",
        "Room 866": "6.31e+92",
        "Room 867": "6.95e+92",
        "Room 868": "7.64e+92",
        "Room 869": "8.40e+92",
        "Room 870": "9.24e+92",
        "Room 871": "1.02e+93",
        "Room 872": "1.12e+93",
        "Room 873": "1.23e+93",
        "Room 874": "1.35e+93",
        "Room 875": "1.49e+93",
        "Room 876": "1.64e+93",
        "Room 877": "1.80e+93",
        "Room 878": "1.98e+93",
        "Room 879": "2.18e+93",
        "Room 880": "2.40e+93",
        "Room 881": "2.64e+93",
        "Room 882": "2.90e+93",
        "Room 883": "3.19e+93",
        "Room 884": "3.51e+93",
        "Room 885": "3.86e+93",
        "Room 886": "4.25e+93",
        "Room 887": "4.67e+93",
        "Room 888": "5.14e+93",
        "Room 889": "5.65e+93",
        "Room 890": "6.22e+93",
        "Room 891": "6.84e+93",
        "Room 892": "7.53e+93",
        "Room 893": "8.28e+93",
        "Room 894": "9.11e+93",
        "Room 895": "1.00e+94",
        "Room 896": "1.10e+94",
        "Room 897": "1.21e+94",
        "Room 898": "1.33e+94",
        "Room 899": "1.47e+94",
        "Room 900": "1.61e+94",
        "Room 901": "1.77e+94",
        "Room 902": "1.95e+94",
        "Room 903": "2.15e+94",
        "Room 904": "2.36e+94",
        "Room 905": "2.60e+94",
        "Room 906": "2.86e+94",
        "Room 907": "3.14e+94",
        "Room 908": "3.46e+94",
        "Room 909": "3.80e+94",
        "Room 910": "4.18e+94",
        "Room 911": "4.60e+94",
        "Room 912": "5.06e+94",
        "Room 913": "5.57e+94",
        "Room 914": "6.13e+94",
        "Room 915": "6.74e+94",
        "Room 916": "7.41e+94",
        "Room 917": "8.15e+94",
        "Room 918": "8.97e+94",
        "Room 919": "9.87e+94",
        "Room 920": "1.09e+95",
        "Room 921": "1.19e+95",
        "Room 922": "1.31e+95",
        "Room 923": "1.44e+95",
        "Room 924": "1.59e+95",
        "Room 925": "1.75e+95",
        "Room 926": "1.92e+95",
        "Room 927": "2.11e+95",
        "Room 928": "2.33e+95",
        "Room 929": "2.56e+95",
        "Room 930": "2.81e+95",
        "Room 931": "3.10e+95",
        "Room 932": "3.41e+95",
        "Room 933": "3.75e+95",
        "Room 934": "4.12e+95",
        "Room 935": "4.53e+95",
        "Room 936": "4.99e+95",
        "Room 937": "5.49e+95",
        "Room 938": "6.03e+95",
        "Room 939": "6.64e+95",
        "Room 940": "7.30e+95",
        "Room 941": "8.03e+95",
        "Room 942": "8.83e+95",
        "Room 943": "9.72e+95",
        "Room 944": "1.07e+96",
        "Room 945": "1.18e+96",
        "Room 946": "1.29e+96",
        "Room 947": "1.42e+96",
        "Room 948": "1.56e+96",
        "Room 949": "1.72e+96",
        "Room 950": "1.89e+96",
        "Room 951": "2.08e+96",
        "Room 952": "2.29e+96",
        "Room 953": "2.52e+96",
        "Room 954": "2.77e+96",
        "Room 955": "3.05e+96",
        "Room 956": "3.35e+96",
        "Room 957": "3.69e+96",
        "Room 958": "4.06e+96",
        "Room 959": "4.47e+96",
        "Room 960": "4.91e+96",
        "Room 961": "5.40e+96",
        "Room 962": "5.94e+96",
        "Room 963": "6.54e+96",
        "Room 964": "7.19e+96",
        "Room 965": "7.91e+96",
        "Room 966": "8.70e+96",
        "Room 967": "9.57e+96",
        "Room 968": "1.05e+97",
        "Room 969": "1.16e+97",
        "Room 970": "1.27e+97",
        "Room 971": "1.40e+97",
        "Room 972": "1.54e+97",
        "Room 973": "1.70e+97",
        "Room 974": "1.87e+97",
        "Room 975": "2.05e+97",
        "Room 976": "2.26e+97",
        "Room 977": "2.48e+97",
        "Room 978": "2.73e+97",
        "Room 979": "3.00e+97",
        "Room 980": "3.30e+97",
        "Room 981": "3.64e+97",
        "Room 982": "4.00e+97",
        "Room 983": "4.40e+97",
        "Room 984": "4.84e+97",
        "Room 985": "5.32e+97",
        "Room 986": "5.85e+97",
        "Room 987": "6.44e+97",
        "Room 988": "7.08e+97",
        "Room 989": "7.79e+97",
        "Room 990": "8.57e+97",
        "Room 991": "9.43e+97",
        "Room 992": "1.04e+98",
        "Room 993": "1.14e+98",
        "Room 994": "1.25e+98",
        "Room 995": "1.38e+98",
        "Room 996": "1.52e+98",
        "Room 997": "1.67e+98",
        "Room 998": "1.84e+98",
        "Room 999": "2.02e+98",
        "Room 1000": "2.22e+98"
    }
}